README.rst
setup.py
pyaptly/__init__.py
pyaptly/aptly_test.py
pyaptly/dateround_test.py
pyaptly/delete_merge.yml
pyaptly/delete_test.yml
pyaptly/graph_test.py
pyaptly/helpers_test.py
pyaptly/merge.yml
pyaptly/mirror-google.yml
pyaptly/mirror-no-google.yml
pyaptly/mirror.yml
pyaptly/publish-current.yml
pyaptly/publish-previous.yml
pyaptly/publish.yml
pyaptly/publish_publish.yml
pyaptly/publish_repo.yml
pyaptly/repo.yml
pyaptly/snapshot-current.yml
pyaptly/snapshot.yml
pyaptly/snapshot_filter.yml
pyaptly/snapshot_merge.yml
pyaptly/snapshot_repo.yml
pyaptly/test.py
pyaptly/test01.yml
pyaptly/test_test.py
pyaptly/version.py
pyaptly.egg-info/PKG-INFO
pyaptly.egg-info/SOURCES.txt
pyaptly.egg-info/dependency_links.txt
pyaptly.egg-info/entry_points.txt
pyaptly.egg-info/requires.txt
pyaptly.egg-info/top_level.txt