Metadata-Version: 1.1
Name: pyaptly
Version: 1.2.0
Summary: Aptly mirror/snapshot managment automation.
Home-page: https://github.com/adfinis-sygroup/pyaptly
Author: Adfinis-SyGroup
Author-email: https://adfinis-sygroup.ch/
License: UNKNOWN
Keywords: aptly mirror snapshot automation
Platform: UNKNOWN
Classifier: Development Status :: 5 - Production/Stable
Classifier: Environment :: Console
Classifier: Intended Audience :: Developers
Classifier: Intended Audience :: Information Technology
Classifier: License :: OSI Approved :: GNU Affero General Public License v3
Classifier: Natural Language :: English
Classifier: Operating System :: OS Independent
Classifier: Programming Language :: Python :: 2.6
Classifier: Programming Language :: Python :: 2.7
Classifier: Programming Language :: Python :: 3.4
Classifier: Programming Language :: Python :: 3.5
